LICENSE
MANIFEST.in
README.md
setup.py
src/textbrewer/__init__.py
src/textbrewer/compatibility.py
src/textbrewer/configurations.py
src/textbrewer/data_utils.py
src/textbrewer/distiller_basic.py
src/textbrewer/distiller_general.py
src/textbrewer/distiller_multitask.py
src/textbrewer/distiller_multiteacher.py
src/textbrewer/distiller_train.py
src/textbrewer/distiller_utils.py
src/textbrewer/distillers.py
src/textbrewer/losses.py
src/textbrewer/presets.py
src/textbrewer/projections.py
src/textbrewer/schedulers.py
src/textbrewer/snippet.py
src/textbrewer/utils.py
src/textbrewer.egg-info/PKG-INFO
src/textbrewer.egg-info/SOURCES.txt
src/textbrewer.egg-info/dependency_links.txt
src/textbrewer.egg-info/requires.txt
src/textbrewer.egg-info/top_level.txt