Metadata-Version: 2.1
Name: textbrewer
Version: 0.2.1
Summary: PyTorch-based knowledge distillation toolkit for natural language processing
Home-page: http://textbrewer.hfl-rc.com
Author: ziqingyang
Author-email: zqyang5@iflytek.com
License: UNKNOWN
Keywords: NLP deep learning knowledge distillation pytorch
Platform: UNKNOWN
Classifier: Intended Audience :: Developers
Classifier: Intended Audience :: Education
Classifier: Intended Audience :: Science/Research
Classifier: License :: OSI Approved :: Apache Software License
Classifier: Operating System :: OS Independent
Classifier: Programming Language :: Python :: 3.6
Classifier: Programming Language :: Python :: 3.7
Classifier: Topic :: Scientific/Engineering :: Artificial Intelligence
Requires-Python: >=3.6
